langchain_logseq/__init__.py
langchain_logseq/loaders/__init__.py
langchain_logseq/loaders/journal_document_metadata.py
langchain_logseq/loaders/journal_filesystem_loader.py
langchain_logseq/loaders/journal_loader.py
langchain_logseq/loaders/journal_loader_input.py
langchain_logseq/models/__init__.py
langchain_logseq/models/journal_pgvector.py
langchain_logseq/retrievers/__init__.py
langchain_logseq/retrievers/contextualizer.py
langchain_logseq/retrievers/journal_date_range_retriever.py
langchain_logseq/retrievers/journal_retriever.py
langchain_logseq/retrievers/pgvector_journal_retriever.py
langchain_logseq/uploaders/__init__.py
langchain_logseq/uploaders/pgvector/__init__.py
langchain_logseq/uploaders/pgvector/journal_corpus_manager.py
langchain_logseq-0.3.2.dist-info/LICENSE
langchain_logseq-0.3.2.dist-info/METADATA
langchain_logseq-0.3.2.dist-info/WHEEL
langchain_logseq-0.3.2.dist-info/top_level.txt
langchain_logseq-0.3.2.dist-info/RECORD
