Metadata-Version: 2.1
Name: langchain-logseq
Version: 0.3.2
Summary: LangChain helpers for working with Logseq documents
Author-email: DL <v49t9zpqd@mozmail.com>
License: MIT
Classifier: Programming Language :: Python :: 3
Classifier: License :: OSI Approved :: MIT License
Classifier: Operating System :: OS Independent
Requires-Python: >=3.11
License-File: LICENSE
Requires-Dist: langchain<0.4.0,>=0.3.24
Requires-Dist: pydantic<3.0,>=2.11
Requires-Dist: pgvector-template>=0.3.1
Provides-Extra: scripts
Requires-Dist: python-dotenv; extra == "scripts"
Requires-Dist: psycopg2-binary>=2.9.0; extra == "scripts"
Requires-Dist: langchain-aws>=0.2.0; extra == "scripts"
Provides-Extra: test
Requires-Dist: pytest; extra == "test"
Requires-Dist: pytest-cov; extra == "test"
Requires-Dist: python-dotenv; extra == "test"
Requires-Dist: boto3; extra == "test"
Requires-Dist: boto3-stubs; extra == "test"
Requires-Dist: langchain-aws>=0.2.0; extra == "test"
Requires-Dist: psycopg[binary]>=3.0.0; extra == "test"
